devknife/__init__.py
devknife/main.py
devknife/cli/__init__.py
devknife/cli/main.py
devknife/core/__init__.py
devknife/core/config_manager.py
devknife/core/error_handling.py
devknife/core/interfaces.py
devknife/core/io_handler.py
devknife/core/models.py
devknife/core/performance.py
devknife/core/router.py
devknife/tui/__init__.py
devknife/tui/app.css
devknife/tui/app.py
devknife/utils/__init__.py
devknife/utils/data_format_utility.py
devknife/utils/developer_utility.py
devknife/utils/encoding_utility.py
devknife/utils/example_utility.py
devknife/utils/math_utility.py
devknife/utils/web_utility.py
nalutbae_dev_knife-0.1.0.dist-info/licenses/LICENSE
nalutbae_dev_knife-0.1.0.dist-info/METADATA
nalutbae_dev_knife-0.1.0.dist-info/WHEEL
nalutbae_dev_knife-0.1.0.dist-info/entry_points.txt
nalutbae_dev_knife-0.1.0.dist-info/top_level.txt
nalutbae_dev_knife-0.1.0.dist-info/RECORD
