Metadata-Version: 2.4
Name: nalutbae-dev-knife
Version: 0.1.0
Summary: An all-in-one terminal toolkit that integrates everyday developer utilities.
Author-email: DevKnife Team <team@devknife.com>
License: MIT
Project-URL: Homepage, https://github.com/nalutebae/nalutbae-dev-knife
Project-URL: Documentation, https://github.com/nalutebae/nalutbae-dev-knife#readme
Project-URL: Repository, https://github.com/nalutebae/nalutbae-dev-knife.git
Project-URL: Issues, https://github.com/nalutebae/nalutbae-dev-knife/issues
Project-URL: Changelog, https://github.com/nalutebae/nalutbae-dev-knife/blob/main/CHANGELOG.md
Keywords: developer-tools,cli,tui,utilities,encoding,json,xml,yaml,base64,url-encoding,csv,markdown,uuid,hash,timestamp,graphql,css,terminal,devtools
Classifier: Development Status :: 4 - Beta
Classifier: Environment :: Console
Classifier: Environment :: Console :: Curses
Classifier: Intended Audience :: Developers
Classifier: Intended Audience :: System Administrators
Classifier: License :: OSI Approved :: MIT License
Classifier: Operating System :: OS Independent
Classifier: Programming Language :: Python :: 3
Classifier: Programming Language :: Python :: 3.8
Classifier: Programming Language :: Python :: 3.9
Classifier: Programming Language :: Python :: 3.10
Classifier: Programming Language :: Python :: 3.11
Classifier: Programming Language :: Python :: 3.12
Classifier: Topic :: Software Development :: Libraries :: Python Modules
Classifier: Topic :: System :: Systems Administration
Classifier: Topic :: Terminals
Classifier: Topic :: Text Processing
Classifier: Topic :: Utilities
Requires-Python: >=3.8
License-File: LICENSE
Requires-Dist: click>=8.0.0
Requires-Dist: textual>=0.40.0
Requires-Dist: chardet>=5.0.0
Requires-Dist: PyYAML>=6.0.0
Provides-Extra: dev
Requires-Dist: pytest>=7.0.0; extra == "dev"
Requires-Dist: pytest-cov; extra == "dev"
Requires-Dist: hypothesis>=6.0.0; extra == "dev"
Requires-Dist: black; extra == "dev"
Requires-Dist: flake8; extra == "dev"
Requires-Dist: mypy; extra == "dev"
Requires-Dist: build; extra == "dev"
Requires-Dist: twine; extra == "dev"
Provides-Extra: test
Requires-Dist: pytest>=7.0.0; extra == "test"
Requires-Dist: pytest-cov; extra == "test"
Requires-Dist: hypothesis>=6.0.0; extra == "test"
Dynamic: license-file
